{

    "embeddings":[
        {
            "tensorName": "classificação",
            "tensorShape": [
                669,
                2
            ],
            "tensorPath": "classificação/tensors.tsv",
            "metadataPath": "classificação/metadata.tsv"
        },
        {
            "tensorName": "clusterização",
            "tensorShape": [
                14999,
                10
            ],
            "tensorPath": "clusterização/tensors.tsv"
        },
        {
            "tensorName": "regressão",
            "tensorShape": [
                714,
                7
            ],
            "tensorPath": "regressão/tensors.tsv",
            "metadataPath": "regressão/metadata.tsv"
        }
    ]
}
